__init__.py
_datetime_utils.py
_exceptions.py
health_ping.py
health_ping-1.0.0.dist-info/METADATA
health_ping-1.0.0.dist-info/WHEEL
health_ping-1.0.0.dist-info/licenses/LICENSE
health_ping-1.0.0.dist-info/RECORD
