Metadata-Version: 2.1
Name: health_ping
Version: 1.0.0
Summary: A lightweight utility package for pinging healthchecks to indicate liveness.
Project-URL: Homepage, https://github.com/tjtanjin/health_ping
Project-URL: Issues, https://github.com/tjtanjin/health_ping/issues
Author-email: tjtanjin <cjtanjin@gmail.com>
License-File: LICENSE
Classifier: License :: OSI Approved :: MIT License
Classifier: Operating System :: OS Independent
Classifier: Programming Language :: Python :: 3
Requires-Python: >=3.0
Requires-Dist: crontab>=0.23.0
